logsentinelai/__init__.py
logsentinelai/cli.py
logsentinelai/py.typed
logsentinelai/analyzers/__init__.py
logsentinelai/analyzers/general_log.py
logsentinelai/analyzers/httpd_access.py
logsentinelai/analyzers/httpd_server.py
logsentinelai/analyzers/linux_system.py
logsentinelai/core/__init__.py
logsentinelai/core/commons.py
logsentinelai/core/config.py
logsentinelai/core/elasticsearch.py
logsentinelai/core/geoip.py
logsentinelai/core/llm.py
logsentinelai/core/monitoring.py
logsentinelai/core/prompts.py
logsentinelai/core/ssh.py
logsentinelai/core/token_utils.py
logsentinelai/core/utils.py
logsentinelai/utils/__init__.py
logsentinelai/utils/geoip_downloader.py
logsentinelai/utils/geoip_lookup.py
logsentinelai-2025.8.12.18.9.42.dist-info/METADATA
logsentinelai-2025.8.12.18.9.42.dist-info/WHEEL
logsentinelai-2025.8.12.18.9.42.dist-info/entry_points.txt
logsentinelai-2025.8.12.18.9.42.dist-info/licenses/LICENSE
logsentinelai-2025.8.12.18.9.42.dist-info/RECORD
