Metadata-Version: 2.4
Name: logsentinelai
Version: 2025.8.12.18.9.42
Summary: AI-Powered Log Analyzer - Leverages LLM to analyze log files and detect security events
Project-URL: Homepage, https://github.com/call518/LogSentinelAI
Project-URL: Repository, https://github.com/call518/LogSentinelAI.git
Project-URL: Issues, https://github.com/call518/LogSentinelAI/issues
Project-URL: Documentation, https://github.com/call518/LogSentinelAI#readme
Author-email: JungJungIn <call518@gmail.com>
License: MIT
License-File: LICENSE
Keywords: ai,cybersecurity,elasticsearch,llm,log-analysis,security,threat-detection
Classifier: Development Status :: 4 - Beta
Classifier: Intended Audience :: Developers
Classifier: Intended Audience :: System Administrators
Classifier: License :: OSI Approved :: MIT License
Classifier: Operating System :: OS Independent
Classifier: Programming Language :: Python :: 3
Classifier: Programming Language :: Python :: 3.11
Classifier: Programming Language :: Python :: 3.12
Classifier: Topic :: Security
Classifier: Topic :: Software Development :: Libraries :: Python Modules
Classifier: Topic :: System :: Logging
Classifier: Topic :: System :: Monitoring
Requires-Python: >=3.11
Requires-Dist: aiohttp>=3.12.14
Requires-Dist: anyio>=4.9.0
Requires-Dist: distro>=1.9.0
Requires-Dist: elastic-transport>=8.17.1
Requires-Dist: elasticsearch>=9.0.2
Requires-Dist: geoip2>=5.1.0
Requires-Dist: google-genai>=1.28.0
Requires-Dist: httpx>=0.28.1
Requires-Dist: interegular>=0.3.3
Requires-Dist: iso3166>=2.1.1
Requires-Dist: jinja2>=3.1.6
Requires-Dist: jiter>=0.10.0
Requires-Dist: jsonpath-ng>=1.7.0
Requires-Dist: maxminddb>=2.7.0
Requires-Dist: ollama>=0.5.1
Requires-Dist: openai>=1.97.1
Requires-Dist: outlines-core>=0.1.26
Requires-Dist: outlines[gemini]>=1.1.1
Requires-Dist: paramiko>=3.5.1
Requires-Dist: pydantic-core>=2.33.2
Requires-Dist: pydantic>=2.11.7
Requires-Dist: python-dateutil>=2.9.0.post0
Requires-Dist: python-dotenv>=1.1.1
Requires-Dist: requests>=2.32.4
Requires-Dist: rich>=14.1.0
Requires-Dist: sniffio>=1.3.1
Requires-Dist: tiktoken>=0.7.0
Requires-Dist: tqdm>=4.67.1
Requires-Dist: typing-extensions>=4.14.1
Provides-Extra: dev
Requires-Dist: black>=23.0; extra == 'dev'
Requires-Dist: flake8>=6.0; extra == 'dev'
Requires-Dist: isort>=5.12; extra == 'dev'
Requires-Dist: mypy>=1.0; extra == 'dev'
Requires-Dist: pytest-asyncio>=0.21.0; extra == 'dev'
Requires-Dist: pytest-cov>=4.0; extra == 'dev'
Requires-Dist: pytest>=7.0; extra == 'dev'
